#These are ignored

#Empty lines are ignored, too

<Forecaster>
	<Debugger>
		Verbose = false
		ScreenOutput  = true
		FileOutput	= true
		OutFilePath  = C:\temp\logs
	</Debugger>
	<Data>
		<Shape>
			SampleLen		= 100
			PredictionLen	= 5
			FeaturesCount	= 4
		</Shape>
		<Train>
			<Debugger>
				Verbose = false
				ScreenOutput  = true
				FileOutput	= true
				OutFilePath  = C:\temp\logs
			</Debugger>
			Do	= true
			<DataSet>
				<TimeSerie>
					Date0				= 201712300000
					HistoryLen			= 505
					DataTransformation	= DT_DELTALOG
					BWCalc				= true
					StatisticalFeatures	= TSF_HISTVOL, TSF_KURTOSIS, TSF_MEAN
					<FXDB_DataSource>
						Symbol				= EURUSD
						TimeFrame			= H1
						IsFilled			= false
						<DBConnection>
							UserName	= History
							Password	= HistoryPwd
							ConnString	= Algo
						</DBConnection>
					</FXDB_DataSource>
				</TimeSerie>
				BatchSamplesCount	= 50
				SelectedFeatures	= FXOPEN, FXHIGH, FXLOW, FXCLOSE
				BWFeatures			= 1,2
			</DataSet>
		</Train>
		<Validation>
			Do	= false
		</Validation>
		<Test>
			Do	= true
			<DataSet>
				<TimeSerie>
					Date0				= 201612300000abc
					HistoryLen			= 100
					DataTransformation	= DT_DELTALOG
					BWCalc				= true
					StatisticalFeatures	= TSF_HISTVOL, TSF_KURTOSIS, TSF_MEAN
					<File_DataSource>
						FileName = C:/temp/SunSpots.txt
						FieldSep = TAB_SEPARATOR
						CalcBW = true
						BWfeatureH = 4
						BWfeatureL = 5
					</File_DataSource>
				</TimeSerie>
				BatchSamplesCount	= 50
				SelectedFeatures	= FXOPEN, FXHIGH, FXLOW, FXCLOSE
				BWFeatures			= 1,2
			</DataSet>
		</Test>
	</Data>
	<Engine>
		<Debugger>
			Verbose 		= true
			Timing			= false
			PauseOnError	= true
			Dest			= DBG_DEST_BOTH
			OutFileFullName	= C:\temp\logs\mainDebugger.log
		</Debugger>		
		Type 		= ENGINE_CUSTOM
		<Custom>
			CoresCount	= 5
			<Core0>
				Type			= CORE_NN
				Parents			= 
				ParentsConnType	= 
				<Topology>
					LevelRatio			= 1,1,1,0.5
					LevelActivation		= NN_ACTIVATION_TANH,NN_ACTIVATION_TANH,NN_ACTIVATION_TANH, NN_ACTIVATION_TANH, NN_ACTIVATION_TANH
					UseContext			= true
					UseBias				= false
				</Topology>
				<Training>
					MaxEpochs			= 50
					TargetMSE			= 0.0001
					NetSaveFrequency	= 10
					StopOnDivergence	= true
					BP_Algo				= BP_STD
					<BP_Std>
						LearningRate		= 0.01
						LearningMomentum	= 0.4
					</BP_Std>
					<BP_Qing>
					</BP_Qing>
					<BP_Qprop>
					</BP_Qprop>
					<BP_RProp>
					</BP_RProp>
				</Training>
			</Core0>
			<Core1>
				Type			= CORE_NN
				Parents			= 
				ParentsConnType	= 
				<Topology>
					LevelRatio			= 1,1,1,0.5
					LevelActivation		= NN_ACTIVATION_TANH,NN_ACTIVATION_TANH,NN_ACTIVATION_TANH, NN_ACTIVATION_TANH, NN_ACTIVATION_TANH
					UseContext			= true
					UseBias				= false
				</Topology>
				<Training>
					MaxEpochs			= 50
					TargetMSE			= 0.0001
					NetSaveFrequency	= 10
					StopOnDivergence	= true
					BP_Algo				= BP_STD
					<BP_Std>
						LearningRate		= 0.01
						LearningMomentum	= 0.4
					</BP_Std>
					<BP_Qing>
					</BP_Qing>
					<BP_Qprop>
					</BP_Qprop>
					<BP_RProp>
					</BP_RProp>
				</Training>
			</Core1>
			<Core2>
				Type			= CORE_GA
				Parents			= Core0
				ParentsConnType	= CONN_DENSE
				<Topology>
					LevelRatio			= 1,1,1,0.5
					LevelActivation		= NN_ACTIVATION_TANH,NN_ACTIVATION_TANH,NN_ACTIVATION_TANH, NN_ACTIVATION_TANH, NN_ACTIVATION_TANH
					UseContext			= true
					UseBias				= false
				</Topology>
				<Training>
					MaxEpochs			= 50
					TargetMSE			= 0.0001
					NetSaveFrequency	= 10
					StopOnDivergence	= true
					BP_Algo				= BP_STD
					<BP_Std>
						LearningRate		= 0.01
						LearningMomentum	= 0.4
					</BP_Std>
					<BP_Qing>
					</BP_Qing>
					<BP_Qprop>
					</BP_Qprop>
					<BP_RProp>
					</BP_RProp>
				</Training>
			</Core2>
			<Core3>
				Type			= CORE_SVM
				Parents			= Core1
				ParentsConnType	= CONN_DENSE
				<Topology>
					LevelRatio			= 1,1,1,0.5
					LevelActivation		= NN_ACTIVATION_TANH,NN_ACTIVATION_TANH,NN_ACTIVATION_TANH, NN_ACTIVATION_TANH, NN_ACTIVATION_TANH
					UseContext			= true
					UseBias				= false
				</Topology>
				<Training>
					MaxEpochs			= 50
					TargetMSE			= 0.0001
					NetSaveFrequency	= 10
					StopOnDivergence	= true
					BP_Algo				= BP_STD
					<BP_Std>
						LearningRate		= 0.01
						LearningMomentum	= 0.4
					</BP_Std>
					<BP_Qing>
					</BP_Qing>
					<BP_Qprop>
					</BP_Qprop>
					<BP_RProp>
					</BP_RProp>
				</Training>
			</Core3>
			<Core4>			
				Type			= CORE_NN
				Parents			= Core2, Core3
				ParentsConnType	= CONN_DENSE, CONN_LINEAR
				<Topology>
					LevelRatio			= 1,1,1,0.5
					LevelActivation		= NN_ACTIVATION_TANH,NN_ACTIVATION_TANH,NN_ACTIVATION_TANH, NN_ACTIVATION_TANH, NN_ACTIVATION_TANH
					UseContext			= true
					UseBias				= false
				</Topology>
				<Training>
					MaxEpochs			= 50
					TargetMSE			= 0.0001
					NetSaveFrequency	= 10
					StopOnDivergence	= true
					BP_Algo				= BP_STD
					<BP_Std>
						LearningRate		= 0.01
						LearningMomentum	= 0.4
					</BP_Std>
					<BP_Qing>
					</BP_Qing>
					<BP_Qprop>
					</BP_Qprop>
					<BP_RProp>
					</BP_RProp>
				</Training>
			</Core4>
		</Custom>
		<XIE>
		</XIE>
		<WNN>
		</WNN>
	</Engine>
	<Persistor>
		saveNothing		= false
		saveClient		= true
		saveMSE			  = true
		saveRun			  = true
		saveInternals	= false
		saveImage		  = true
		Destination      = ORCL_DEST
		<DestDB>
			UserName			  = cuLogUser
			Password		= LogPwd
			ConnString	= Algo
		</DestDB>
		<DestFiles>      
		</DestFiles>
	</Persistor>
</Forecaster>
